cma/__init__.py
cma/bbobbenchmarks.py
cma/boundary_handler.py
cma/constraints_handler.py
cma/evolution_strategy.py
cma/fitness_functions.py
cma/fitness_models.py
cma/fitness_transformations.py
cma/integer_centering.py
cma/interfaces.py
cma/logger.py
cma/optimization_tools.py
cma/options_parameters.py
cma/purecma.py
cma/recombination_weights.py
cma/restricted_gaussian_sampler.py
cma/s.py
cma/sampler.py
cma/sigma_adaptation.py
cma/test.py
cma/transformations.py
cma/wrapper.py
cma/utilities/__init__.py
cma/utilities/math.py
cma/utilities/python3for2.py
cma/utilities/utils.py
cma-4.4.2.dist-info/licenses/LICENSE
cma-4.4.2.dist-info/METADATA
cma-4.4.2.dist-info/WHEEL
cma-4.4.2.dist-info/top_level.txt
cma-4.4.2.dist-info/RECORD
