Metadata-Version: 2.4
Name: cma
Version: 4.4.2
Summary: CMA-ES, Covariance Matrix Adaptation Evolution Strategy for non-linear numerical optimization in Python
Author: Nikolaus Hansen, Youhei Akimoto, Petr Baudis
Maintainer-email: Nikolaus Hansen <authors_firstname.lastname@inria.fr>
License-Expression: BSD-3-Clause
Project-URL: Homepage, https://github.com/CMA-ES/pycma
Project-URL: Repository, https://github.com/CMA-ES/pycma.git
Project-URL: Bug Tracker, https://github.com/CMA-ES/pycma/issues
Keywords: optimization,CMA-ES,cmaes
Classifier: Development Status :: 5 - Production/Stable
Classifier: Environment :: Console
Classifier: Framework :: IPython
Classifier: Framework :: Jupyter
Classifier: Intended Audience :: Education
Classifier: Intended Audience :: Other Audience
Classifier: Intended Audience :: Science/Research
Classifier: Operating System :: OS Independent
Classifier: Programming Language :: Python :: 2.7
Classifier: Programming Language :: Python :: 3
Classifier: Topic :: Scientific/Engineering
Classifier: Topic :: Scientific/Engineering :: Artificial Intelligence
Classifier: Topic :: Scientific/Engineering :: Mathematics
License-File: LICENSE
Requires-Dist: numpy
Provides-Extra: plotting
Requires-Dist: matplotlib; extra == "plotting"
Provides-Extra: constrained-solution-tracking
Requires-Dist: moarchiving; extra == "constrained-solution-tracking"
Dynamic: license-file
